{
  "contracts": [
    {
      "name": "IntegratedRegistryContract",
      "type": "domain_registry",
      "version": "1.0.0",
      "features": [
        "adaptive_pricing",
        "revenue_distribution", 
        "governance_integration",
        "auto_renewal",
        "market_analysis"
      ],
      "address": "nym_contract_1234567890abcdef",
      "admin": "nym1qjk2rem9dq6h2c5tqjlsmlzc4asl4xjxz8p2k",
      "configuration": {
        "burn_percentage": 0.15,
        "max_voting_power": 100000,
        "proposal_threshold": 10000,
        "market_analysis_enabled": true
      }
    },
    {
      "name": "GovernanceContract", 
      "type": "governance",
      "version": "1.0.0",
      "features": [
        "quadratic_voting",
        "delegation",
        "timelock_execution",
        "emergency_actions"
      ],
      "address": "nym_governance_abcdef1234567890",
      "configuration": {
        "voting_period": 604800,
        "timelock_period": 172800,
        "execution_window": 259200
      }
    },
    {
      "name": "AdaptivePricingContract",
      "type": "pricing_engine", 
      "version": "1.0.0",
      "features": [
        "market_indicators",
        "trend_analysis",
        "price_predictions",
        "volatility_protection"
      ],
      "address": "nym_pricing_fedcba0987654321"
    }
  ],
  "deployment_timestamp": "2025-01-07T12:00:00Z",
  "network": "nym-enhanced-testnet"
}
